gmail/gmail.py
python_gmail-0.0.8.dist-info/LICENSE
python_gmail-0.0.8.dist-info/METADATA
python_gmail-0.0.8.dist-info/WHEEL
python_gmail-0.0.8.dist-info/top_level.txt
python_gmail-0.0.8.dist-info/RECORD
