Metadata-Version: 2.1
Name: python-gmail
Version: 0.0.8
Summary: Automatically Send Gmail with SMTP Server.
Home-page: https://github.com/sujitmandal/py-gmail
Author: Sujit Mandal
Author-email: mandals974@gmail.com
License: MIT
Platform: UNKNOWN
Classifier: License :: OSI Approved :: MIT License
Classifier: Programming Language :: Python :: 2.7
Classifier: Programming Language :: Python :: 3.0
Classifier: Programming Language :: Python :: 3.6
Classifier: Programming Language :: Python :: 3.7
Classifier: Programming Language :: Python :: 3.8
Classifier: Programming Language :: Python :: 3.9
